Metadata-Version: 2.1
Name: pauytinka-vsoh
Version: 1.0
Requires-Dist: requests
